__init__.py
execution.py
simulator.py
xxsim-0.7.0.dist-info/licenses/LICENSE
xxsim-0.7.0.dist-info/METADATA
xxsim-0.7.0.dist-info/WHEEL
xxsim-0.7.0.dist-info/top_level.txt
xxsim-0.7.0.dist-info/RECORD
