Metadata-Version: 2.4
Name: XXSim
Version: 0.7.0
Summary: Exchange Execution Simulator - stock exchange single bar execution simulator
Author-email: Yanir Taflev <yanirta+xxsim@gmail.com>
License: MIT
Keywords: trade,Algotrading,simulation,trading,exchange,stocks,backtesting,stock market,execution simulator,OHLCV,order simulation,finance,trading bot,quantitative,algorithmic trading,market data
Classifier: Programming Language :: Python :: 3.9
Classifier: Programming Language :: Python :: 3.10
Classifier: Programming Language :: Python :: 3.11
Classifier: License :: OSI Approved :: MIT License
Classifier: Operating System :: OS Independent
Requires-Python: >=3.10
License-File: LICENSE
Requires-Dist: numpy
Requires-Dist: pydantic>=2.0
Requires-Dist: xtrading-models>=0.6.0
Provides-Extra: dev
Requires-Dist: plotly; extra == "dev"
Requires-Dist: pandas; extra == "dev"
Dynamic: license-file
